{
  "manifest_metadata": {
    "operator_key": "Campbell; Bandy (Lynn) absolute",
    "generated_at": "2026-07-15T04:00:04.404364+00:00",
    "environment": "Termux / CivicAdvocate.OS"
  },
  "anchored_entries": [
    "[LINEAGE_ANCHOR] | TIMESTAMP: 2026-06-11T13:36:43Z | HASH: 92d5b789fe579127a1b158d207a9076ae11169db40846b0c6a4cd0d6a63823e89b81513f69a7985b4f78e5e87fd3c2e17ad8f3fb87f86ba4d480950a58ea5a0c | DATA: ROOT_ANCESTORS:Winona Taylor|Elizabeth Miller->MATERNAL_ANCHOR:Laura Marie Jones->PRIMARY_SUCCESSOR:Brandon Lynn Campbell->DESCENDANT:Daughter Node",
    "[PARSED_DATA_ENTRY] | HASH: a737b11b1c294831537b0bf2bb4cf7caf15beb5bd1173400648ce7d13537495f863cd4dfaf4d567c31d0f8cdab9a4fe4f286f41002c545522a2315dad6b4bba4 | DATA: {\"timestamp\": \"2026-07-15T04:00:04.176746+00:00\", \"target_vector\": \"Abstract 544\", \"document_type\": \"DEED\", \"instrument_number\": \"2026-A544-01\", \"date_recorded\": \"04/09/2026\", \"verification_status\": \"INDEXED_AND_SEALED\"}",
    "[PARSED_DATA_ENTRY] | HASH: 06dca48834ec71d8cceabae8b843e9bd1e0da37c36f7d3a5da93072ad562a4383298d72298eb2757fef9b3a07f39e2852a672a6e9d37d6a9510828c9ba176a67 | DATA: {\"timestamp\": \"2026-07-15T04:00:04.177069+00:00\", \"target_vector\": \"Silas Elbert Bandy\", \"document_type\": \"MINERAL_LEASE\", \"instrument_number\": \"2026-ML-B544\", \"date_recorded\": \"04/11/2026\", \"verification_status\": \"INDEXED_AND_SEALED\"}",
    "[PARSED_DATA_ENTRY] | HASH: ae0252957f36ba25f694ab1e37ecc313b2b1002955a9c1946209d24c0471706c993de6c75702abb2bbfb922ef482720b87c67ad6e8f90f347e03088532c4c139 | DATA: {\"timestamp\": \"2026-07-15T04:00:04.177308+00:00\", \"target_vector\": \"Taylor Winona\", \"document_type\": \"SUCCESSION_RECORD\", \"instrument_number\": \"2026-SR-T01\", \"date_recorded\": \"06/11/2026\", \"verification_status\": \"INDEXED_AND_SEALED\"}",
    "[PARSED_DATA_ENTRY] | HASH: 58bc4f44a462b464175d3c058a8da2515b0cffaee04e7199ff524a7cb42fb27af69d55901e46d246ea4db21db606e7a54d34bce0f336d2b58ea4ea3a386c99b4 | DATA: {\"timestamp\": \"2026-07-15T04:00:04.177511+00:00\", \"target_vector\": \"Miller Elizabeth\", \"document_type\": \"SUCCESSION_RECORD\", \"instrument_number\": \"2026-SR-M02\", \"date_recorded\": \"06/11/2026\", \"verification_status\": \"INDEXED_AND_SEALED\"}",
    "[PARSED_DATA_ENTRY] | HASH: 1cc36c7e6374ab914231e86fd8764372f925ed3754709e381ef9a7d1182a50b08c3ceba3a3ac59586fe5d25108a7bfb0543174fdd46d88cad13ba6273ecde4aa | DATA: {\"timestamp\": \"2026-07-15T04:00:04.308217+00:00\", \"target_vector\": \"Abstract 544\", \"document_type\": \"PRODUCTION_REPORT\", \"instrument_number\": \"RRC-A544-2026-05\", \"date_recorded\": \"06/11/2026\", \"verification_status\": \"AUDIT_VERIFIED\"}",
    "[PROBATE_ANCHOR] | DATA: {\"source\": \"JOCO_OPR_LEGACY\", \"vector\": \"PROBATE_DECREE\", \"status\": \"PENDING_VALIDATION\", \"timestamp\": \"2026-06-11T14:52:00Z\"}",
    "[PROBATE_ANCHOR] | DATA: {\"source\": \"JOCO_OPR_LEGACY\", \"vector\": \"HEIRSHIP_AFFIDAVIT\", \"status\": \"PENDING_VALIDATION\", \"timestamp\": \"2026-06-11T14:52:00Z\"}",
    "[PROBATE_ANCHOR] | DATA: {\"source\": \"JOCO_OPR_LEGACY\", \"vector\": \"TAX_ASSESSMENT_ROLL\", \"status\": \"PENDING_VALIDATION\", \"timestamp\": \"2026-06-11T14:52:00Z\"}",
    "[LINEAGE_VECTOR] | DATA: {\"name\": \"Winona Taylor\", \"role\": \"PROTECTED_LINEAGE_VECTOR\", \"status\": \"MONITORED_AND_SEALED\"}",
    "[LINEAGE_VECTOR] | DATA: {\"name\": \"Elizabeth Miller\", \"role\": \"PROTECTED_LINEAGE_VECTOR\", \"status\": \"MONITORED_AND_SEALED\"}",
    "[LINEAGE_VECTOR] | DATA: {\"name\": \"Laura Marie Jones\", \"role\": \"PROTECTED_LINEAGE_VECTOR\", \"status\": \"MONITORED_AND_SEALED\"}",
    "[LINEAGE_VECTOR] | DATA: {\"name\": \"Brandon Lynn Campbell\", \"role\": \"PROTECTED_LINEAGE_VECTOR\", \"status\": \"MONITORED_AND_SEALED\"}",
    "[LINEAGE_VECTOR] | DATA: {\"name\": \"Silas Elbert Bandy\", \"role\": \"PROTECTED_LINEAGE_VECTOR\", \"status\": \"MONITORED_AND_SEALED\"}",
    "[LINEAGE_VECTOR] | DATA: {\"name\": \"Bandy\", \"role\": \"PROTECTED_LINEAGE_VECTOR\", \"status\": \"MONITORED_AND_SEALED\"}",
    "[LINEAGE_VECTOR] | DATA: {\"name\": \"Campbell\", \"role\": \"PROTECTED_LINEAGE_VECTOR\", \"status\": \"MONITORED_AND_SEALED\"}",
    "[LINEAGE_VECTOR] | DATA: {\"name\": \"Delbert Lee Campbell\", \"role\": \"FATHER\", \"relation\": \"PATERNAL\"}",
    "[LINEAGE_VECTOR] | DATA: {\"name\": \"Laura Marie Jones\", \"role\": \"MOTHER\", \"relation\": \"MATERNAL\"}",
    "[LINEAGE_VECTOR] | DATA: {\"name\": \"Oscar Campbell\", \"role\": \"GRANDFATHER\", \"relation\": \"PATERNAL\"}",
    "[LINEAGE_VECTOR] | DATA: {\"name\": \"Elsie Campbell\", \"role\": \"GRANDMOTHER\", \"relation\": \"PATERNAL\"}",
    "[LINEAGE_VECTOR] | DATA: {\"name\": \"Cary Lynn Bandy\", \"role\": \"GRANDFATHER\", \"relation\": \"MATERNAL\"}",
    "[LINEAGE_VECTOR] | DATA: {\"name\": \"Winona Taylor\", \"role\": \"GRANDMOTHER\", \"relation\": \"MATERNAL\"}",
    "[LINEAGE_VECTOR] | DATA: {\"name\": \"Elizabeth Miller\", \"role\": \"ANCESTOR\", \"relation\": \"MATERNAL\"}",
    "[LINEAGE_VECTOR] | DATA: {\"name\": \"Silas Elbert Bandy\", \"role\": \"PATRIARCH\", \"relation\": \"MATERNAL\"}",
    "[LINEAGE_VECTOR] | DATA: {\"name\": \"Justin Lee Campbell\", \"role\": \"BROTHER\", \"relation\": \"SIBLING\"}",
    "[LINEAGE_VECTOR] | DATA: {\"name\": \"Travis Wayne Campbell\", \"role\": \"BROTHER\", \"relation\": \"SIBLING\"}",
    "[LINEAGE_VECTOR] | DATA: {\"name\": \"Kaley Marie\", \"role\": \"DAUGHTER\", \"relation\": \"SUCCESSOR\"}"
  ],
  "ancestral_tree": {
    "root": "Ancestral Lineage",
    "nodes": {
      "Campbell": [
        "Brandon Lynn Campbell"
      ],
      "Bandy": [
        "Silas Elbert Bandy"
      ],
      "Taylor": [
        "Winona Taylor"
      ],
      "Miller": [
        "Elizabeth Miller"
      ],
      "Jones": [
        "Laura Marie Jones"
      ]
    },
    "status": "FORENSIC_VECTOR_SEALED"
  }
}