{
  "manifest_metadata": {
    "operator_key": "Campbell; Bandy (Lynn) absolute",
    "generated_at": "2026-06-22T23:00:03.579453+00:00",
    "environment": "Termux / CivicAdvocate.OS"
  },
  "anchored_entries": [
    "[LINEAGE_ANCHOR] | TIMESTAMP: 2026-06-11T13:36:43Z | HASH: 92d5b789fe579127a1b158d207a9076ae11169db40846b0c6a4cd0d6a63823e89b81513f69a7985b4f78e5e87fd3c2e17ad8f3fb87f86ba4d480950a58ea5a0c | DATA: ROOT_ANCESTORS:Winona Taylor|Elizabeth Miller->MATERNAL_ANCHOR:Laura Marie Jones->PRIMARY_SUCCESSOR:Brandon Lynn Campbell->DESCENDANT:Daughter Node",
    "[PARSED_DATA_ENTRY] | HASH: 09e066c4bfae7fb7569774532cb4b715b317aa7c37a43babcf33b9e8f5be7b349da8cbf194c4a47246a31a482257f70cae3d5c9082e80fc15d9609f9a94f0a81 | DATA: {\"timestamp\": \"2026-06-22T23:00:03.390333+00:00\", \"target_vector\": \"Abstract 544\", \"document_type\": \"DEED\", \"instrument_number\": \"2026-A544-01\", \"date_recorded\": \"04/09/2026\", \"verification_status\": \"INDEXED_AND_SEALED\"}",
    "[PARSED_DATA_ENTRY] | HASH: 0d01533e222d290ffd4deda4311fa0d487297949ca5e130e544533c6fd044bd901ad4a37b2b859ada0b8cf3a60428c26c72cd89c8029672b8a932bdc52b927ea | DATA: {\"timestamp\": \"2026-06-22T23:00:03.390579+00:00\", \"target_vector\": \"Silas Elbert Bandy\", \"document_type\": \"MINERAL_LEASE\", \"instrument_number\": \"2026-ML-B544\", \"date_recorded\": \"04/11/2026\", \"verification_status\": \"INDEXED_AND_SEALED\"}",
    "[PARSED_DATA_ENTRY] | HASH: 8b38735ea1b553b949b14c3f50548fc39ee65e325a6bcb691734e45ff321edb21c667e549997ff07b13ebf70e7fe1e2741893fb279d999680aac596f1546fe4c | DATA: {\"timestamp\": \"2026-06-22T23:00:03.390737+00:00\", \"target_vector\": \"Taylor Winona\", \"document_type\": \"SUCCESSION_RECORD\", \"instrument_number\": \"2026-SR-T01\", \"date_recorded\": \"06/11/2026\", \"verification_status\": \"INDEXED_AND_SEALED\"}",
    "[PARSED_DATA_ENTRY] | HASH: d6d76bf27391fdf4e4cb0bf9a0f86a173d8ab05fc7af5d12a954fe96e9d009e4d430422c2dafba2d145109e39c3f2def520ea6a22539bdd3af8093dded4b1a14 | DATA: {\"timestamp\": \"2026-06-22T23:00:03.390872+00:00\", \"target_vector\": \"Miller Elizabeth\", \"document_type\": \"SUCCESSION_RECORD\", \"instrument_number\": \"2026-SR-M02\", \"date_recorded\": \"06/11/2026\", \"verification_status\": \"INDEXED_AND_SEALED\"}",
    "[PARSED_DATA_ENTRY] | HASH: 1c3c0faa690c502f3fde2b775ca9bb9b8ec64661aaa18e00b96ecfa8b51b6221ef3c87bf1893d7fe139b6b20daeb44aafdd0541d7f1275a97f544abbfbb36bee | DATA: {\"timestamp\": \"2026-06-22T23:00:03.486663+00:00\", \"target_vector\": \"Abstract 544\", \"document_type\": \"PRODUCTION_REPORT\", \"instrument_number\": \"RRC-A544-2026-05\", \"date_recorded\": \"06/11/2026\", \"verification_status\": \"AUDIT_VERIFIED\"}",
    "[PROBATE_ANCHOR] | DATA: {\"source\": \"JOCO_OPR_LEGACY\", \"vector\": \"PROBATE_DECREE\", \"status\": \"PENDING_VALIDATION\", \"timestamp\": \"2026-06-11T14:52:00Z\"}",
    "[PROBATE_ANCHOR] | DATA: {\"source\": \"JOCO_OPR_LEGACY\", \"vector\": \"HEIRSHIP_AFFIDAVIT\", \"status\": \"PENDING_VALIDATION\", \"timestamp\": \"2026-06-11T14:52:00Z\"}",
    "[PROBATE_ANCHOR] | DATA: {\"source\": \"JOCO_OPR_LEGACY\", \"vector\": \"TAX_ASSESSMENT_ROLL\", \"status\": \"PENDING_VALIDATION\", \"timestamp\": \"2026-06-11T14:52:00Z\"}",
    "[LINEAGE_VECTOR] | DATA: {\"name\": \"Winona Taylor\", \"role\": \"PROTECTED_LINEAGE_VECTOR\", \"status\": \"MONITORED_AND_SEALED\"}",
    "[LINEAGE_VECTOR] | DATA: {\"name\": \"Elizabeth Miller\", \"role\": \"PROTECTED_LINEAGE_VECTOR\", \"status\": \"MONITORED_AND_SEALED\"}",
    "[LINEAGE_VECTOR] | DATA: {\"name\": \"Laura Marie Jones\", \"role\": \"PROTECTED_LINEAGE_VECTOR\", \"status\": \"MONITORED_AND_SEALED\"}",
    "[LINEAGE_VECTOR] | DATA: {\"name\": \"Brandon Lynn Campbell\", \"role\": \"PROTECTED_LINEAGE_VECTOR\", \"status\": \"MONITORED_AND_SEALED\"}",
    "[LINEAGE_VECTOR] | DATA: {\"name\": \"Silas Elbert Bandy\", \"role\": \"PROTECTED_LINEAGE_VECTOR\", \"status\": \"MONITORED_AND_SEALED\"}",
    "[LINEAGE_VECTOR] | DATA: {\"name\": \"Bandy\", \"role\": \"PROTECTED_LINEAGE_VECTOR\", \"status\": \"MONITORED_AND_SEALED\"}",
    "[LINEAGE_VECTOR] | DATA: {\"name\": \"Campbell\", \"role\": \"PROTECTED_LINEAGE_VECTOR\", \"status\": \"MONITORED_AND_SEALED\"}",
    "[LINEAGE_VECTOR] | DATA: {\"name\": \"Delbert Lee Campbell\", \"role\": \"FATHER\", \"relation\": \"PATERNAL\"}",
    "[LINEAGE_VECTOR] | DATA: {\"name\": \"Laura Marie Jones\", \"role\": \"MOTHER\", \"relation\": \"MATERNAL\"}",
    "[LINEAGE_VECTOR] | DATA: {\"name\": \"Oscar Campbell\", \"role\": \"GRANDFATHER\", \"relation\": \"PATERNAL\"}",
    "[LINEAGE_VECTOR] | DATA: {\"name\": \"Elsie Campbell\", \"role\": \"GRANDMOTHER\", \"relation\": \"PATERNAL\"}",
    "[LINEAGE_VECTOR] | DATA: {\"name\": \"Cary Lynn Bandy\", \"role\": \"GRANDFATHER\", \"relation\": \"MATERNAL\"}",
    "[LINEAGE_VECTOR] | DATA: {\"name\": \"Winona Taylor\", \"role\": \"GRANDMOTHER\", \"relation\": \"MATERNAL\"}",
    "[LINEAGE_VECTOR] | DATA: {\"name\": \"Elizabeth Miller\", \"role\": \"ANCESTOR\", \"relation\": \"MATERNAL\"}",
    "[LINEAGE_VECTOR] | DATA: {\"name\": \"Silas Elbert Bandy\", \"role\": \"PATRIARCH\", \"relation\": \"MATERNAL\"}",
    "[LINEAGE_VECTOR] | DATA: {\"name\": \"Justin Lee Campbell\", \"role\": \"BROTHER\", \"relation\": \"SIBLING\"}",
    "[LINEAGE_VECTOR] | DATA: {\"name\": \"Travis Wayne Campbell\", \"role\": \"BROTHER\", \"relation\": \"SIBLING\"}",
    "[LINEAGE_VECTOR] | DATA: {\"name\": \"Kaley Marie\", \"role\": \"DAUGHTER\", \"relation\": \"SUCCESSOR\"}"
  ],
  "ancestral_tree": {
    "root": "Ancestral Lineage",
    "nodes": {
      "Campbell": [
        "Brandon Lynn Campbell"
      ],
      "Bandy": [
        "Silas Elbert Bandy"
      ],
      "Taylor": [
        "Winona Taylor"
      ],
      "Miller": [
        "Elizabeth Miller"
      ],
      "Jones": [
        "Laura Marie Jones"
      ]
    },
    "status": "FORENSIC_VECTOR_SEALED"
  }
}