{
  "manifest_metadata": {
    "operator_key": "Campbell; Bandy (Lynn) absolute",
    "generated_at": "2026-06-19T15:00:04.827717+00:00",
    "environment": "Termux / CivicAdvocate.OS"
  },
  "anchored_entries": [
    "[LINEAGE_ANCHOR] | TIMESTAMP: 2026-06-11T13:36:43Z | HASH: 92d5b789fe579127a1b158d207a9076ae11169db40846b0c6a4cd0d6a63823e89b81513f69a7985b4f78e5e87fd3c2e17ad8f3fb87f86ba4d480950a58ea5a0c | DATA: ROOT_ANCESTORS:Winona Taylor|Elizabeth Miller->MATERNAL_ANCHOR:Laura Marie Jones->PRIMARY_SUCCESSOR:Brandon Lynn Campbell->DESCENDANT:Daughter Node",
    "[PARSED_DATA_ENTRY] | HASH: 284a6cce656f59b3e9e59c8f6ceaace817c8d168cfe221e38fa8756f7a3169dc493d281510c47b8f1d85de6d8db5b032bc7571df506e54474936f94d356138d3 | DATA: {\"timestamp\": \"2026-06-19T15:00:04.670941+00:00\", \"target_vector\": \"Abstract 544\", \"document_type\": \"DEED\", \"instrument_number\": \"2026-A544-01\", \"date_recorded\": \"04/09/2026\", \"verification_status\": \"INDEXED_AND_SEALED\"}",
    "[PARSED_DATA_ENTRY] | HASH: 096b780bb504ff7362cf1fdae68b35ced116f3552b94f008013fcc6347ee828bc95da699cef5a7a50f859f006cfe8cb61f999a603c60ff1e56969fee497ec416 | DATA: {\"timestamp\": \"2026-06-19T15:00:04.671209+00:00\", \"target_vector\": \"Silas Elbert Bandy\", \"document_type\": \"MINERAL_LEASE\", \"instrument_number\": \"2026-ML-B544\", \"date_recorded\": \"04/11/2026\", \"verification_status\": \"INDEXED_AND_SEALED\"}",
    "[PARSED_DATA_ENTRY] | HASH: 25868c17aae2ffe5c1bf15a407435fe0585f40ff1c76a7d617c2acd94413946c07378a11723f70ec678b84c2a8e9c841cb6f6e6170cbe1d64cbc61b78ee539c1 | DATA: {\"timestamp\": \"2026-06-19T15:00:04.671424+00:00\", \"target_vector\": \"Taylor Winona\", \"document_type\": \"SUCCESSION_RECORD\", \"instrument_number\": \"2026-SR-T01\", \"date_recorded\": \"06/11/2026\", \"verification_status\": \"INDEXED_AND_SEALED\"}",
    "[PARSED_DATA_ENTRY] | HASH: 4ebf67efc4f96d818bd44a3fda3cc98e6547539d30168fe1c41305ec1d20c1a2cbebf004acd8f7d8763fa067de9598f9a178649145898e4d2d769524c2182242 | DATA: {\"timestamp\": \"2026-06-19T15:00:04.671672+00:00\", \"target_vector\": \"Miller Elizabeth\", \"document_type\": \"SUCCESSION_RECORD\", \"instrument_number\": \"2026-SR-M02\", \"date_recorded\": \"06/11/2026\", \"verification_status\": \"INDEXED_AND_SEALED\"}",
    "[PARSED_DATA_ENTRY] | HASH: 0e749d4d600d8a4901ad548ed162308f73f005de91ff3010f276508152e49629db277ad516c32061952c20adbafac4743275726512c51a6e7d18d78af6a48248 | DATA: {\"timestamp\": \"2026-06-19T15:00:04.751677+00:00\", \"target_vector\": \"Abstract 544\", \"document_type\": \"PRODUCTION_REPORT\", \"instrument_number\": \"RRC-A544-2026-05\", \"date_recorded\": \"06/11/2026\", \"verification_status\": \"AUDIT_VERIFIED\"}",
    "[PROBATE_ANCHOR] | DATA: {\"source\": \"JOCO_OPR_LEGACY\", \"vector\": \"PROBATE_DECREE\", \"status\": \"PENDING_VALIDATION\", \"timestamp\": \"2026-06-11T14:52:00Z\"}",
    "[PROBATE_ANCHOR] | DATA: {\"source\": \"JOCO_OPR_LEGACY\", \"vector\": \"HEIRSHIP_AFFIDAVIT\", \"status\": \"PENDING_VALIDATION\", \"timestamp\": \"2026-06-11T14:52:00Z\"}",
    "[PROBATE_ANCHOR] | DATA: {\"source\": \"JOCO_OPR_LEGACY\", \"vector\": \"TAX_ASSESSMENT_ROLL\", \"status\": \"PENDING_VALIDATION\", \"timestamp\": \"2026-06-11T14:52:00Z\"}",
    "[LINEAGE_VECTOR] | DATA: {\"name\": \"Winona Taylor\", \"role\": \"PROTECTED_LINEAGE_VECTOR\", \"status\": \"MONITORED_AND_SEALED\"}",
    "[LINEAGE_VECTOR] | DATA: {\"name\": \"Elizabeth Miller\", \"role\": \"PROTECTED_LINEAGE_VECTOR\", \"status\": \"MONITORED_AND_SEALED\"}",
    "[LINEAGE_VECTOR] | DATA: {\"name\": \"Laura Marie Jones\", \"role\": \"PROTECTED_LINEAGE_VECTOR\", \"status\": \"MONITORED_AND_SEALED\"}",
    "[LINEAGE_VECTOR] | DATA: {\"name\": \"Brandon Lynn Campbell\", \"role\": \"PROTECTED_LINEAGE_VECTOR\", \"status\": \"MONITORED_AND_SEALED\"}",
    "[LINEAGE_VECTOR] | DATA: {\"name\": \"Silas Elbert Bandy\", \"role\": \"PROTECTED_LINEAGE_VECTOR\", \"status\": \"MONITORED_AND_SEALED\"}",
    "[LINEAGE_VECTOR] | DATA: {\"name\": \"Bandy\", \"role\": \"PROTECTED_LINEAGE_VECTOR\", \"status\": \"MONITORED_AND_SEALED\"}",
    "[LINEAGE_VECTOR] | DATA: {\"name\": \"Campbell\", \"role\": \"PROTECTED_LINEAGE_VECTOR\", \"status\": \"MONITORED_AND_SEALED\"}",
    "[LINEAGE_VECTOR] | DATA: {\"name\": \"Delbert Lee Campbell\", \"role\": \"FATHER\", \"relation\": \"PATERNAL\"}",
    "[LINEAGE_VECTOR] | DATA: {\"name\": \"Laura Marie Jones\", \"role\": \"MOTHER\", \"relation\": \"MATERNAL\"}",
    "[LINEAGE_VECTOR] | DATA: {\"name\": \"Oscar Campbell\", \"role\": \"GRANDFATHER\", \"relation\": \"PATERNAL\"}",
    "[LINEAGE_VECTOR] | DATA: {\"name\": \"Elsie Campbell\", \"role\": \"GRANDMOTHER\", \"relation\": \"PATERNAL\"}",
    "[LINEAGE_VECTOR] | DATA: {\"name\": \"Cary Lynn Bandy\", \"role\": \"GRANDFATHER\", \"relation\": \"MATERNAL\"}",
    "[LINEAGE_VECTOR] | DATA: {\"name\": \"Winona Taylor\", \"role\": \"GRANDMOTHER\", \"relation\": \"MATERNAL\"}",
    "[LINEAGE_VECTOR] | DATA: {\"name\": \"Elizabeth Miller\", \"role\": \"ANCESTOR\", \"relation\": \"MATERNAL\"}",
    "[LINEAGE_VECTOR] | DATA: {\"name\": \"Silas Elbert Bandy\", \"role\": \"PATRIARCH\", \"relation\": \"MATERNAL\"}",
    "[LINEAGE_VECTOR] | DATA: {\"name\": \"Justin Lee Campbell\", \"role\": \"BROTHER\", \"relation\": \"SIBLING\"}",
    "[LINEAGE_VECTOR] | DATA: {\"name\": \"Travis Wayne Campbell\", \"role\": \"BROTHER\", \"relation\": \"SIBLING\"}",
    "[LINEAGE_VECTOR] | DATA: {\"name\": \"Kaley Marie\", \"role\": \"DAUGHTER\", \"relation\": \"SUCCESSOR\"}"
  ],
  "ancestral_tree": {
    "root": "Ancestral Lineage",
    "nodes": {
      "Campbell": [
        "Brandon Lynn Campbell"
      ],
      "Bandy": [
        "Silas Elbert Bandy"
      ],
      "Taylor": [
        "Winona Taylor"
      ],
      "Miller": [
        "Elizabeth Miller"
      ],
      "Jones": [
        "Laura Marie Jones"
      ]
    },
    "status": "FORENSIC_VECTOR_SEALED"
  }
}