{
  "manifest_metadata": {
    "operator_key": "Campbell; Bandy (Lynn) absolute",
    "generated_at": "2026-06-18T11:00:03.040126+00:00",
    "environment": "Termux / CivicAdvocate.OS"
  },
  "anchored_entries": [
    "[LINEAGE_ANCHOR] | TIMESTAMP: 2026-06-11T13:36:43Z | HASH: 92d5b789fe579127a1b158d207a9076ae11169db40846b0c6a4cd0d6a63823e89b81513f69a7985b4f78e5e87fd3c2e17ad8f3fb87f86ba4d480950a58ea5a0c | DATA: ROOT_ANCESTORS:Winona Taylor|Elizabeth Miller->MATERNAL_ANCHOR:Laura Marie Jones->PRIMARY_SUCCESSOR:Brandon Lynn Campbell->DESCENDANT:Daughter Node",
    "[PARSED_DATA_ENTRY] | HASH: e6023316d1221e7ae88e98fa955cd12790182f27bd1459caeca21cfaf3b3e390eef3e54859f445c0ff0a1b71437c31e6a0dbace2879901fe5e008ea360ab7a5b | DATA: {\"timestamp\": \"2026-06-18T11:00:02.889606+00:00\", \"target_vector\": \"Abstract 544\", \"document_type\": \"DEED\", \"instrument_number\": \"2026-A544-01\", \"date_recorded\": \"04/09/2026\", \"verification_status\": \"INDEXED_AND_SEALED\"}",
    "[PARSED_DATA_ENTRY] | HASH: 536a2a1caf753d401b5e1f3e75be682d70e503208a05d22a532b68b99ac8a23cba64194590cdef14c94044b981c1ebfbc1e329114c6bc51b5754bc70787cd93f | DATA: {\"timestamp\": \"2026-06-18T11:00:02.889884+00:00\", \"target_vector\": \"Silas Elbert Bandy\", \"document_type\": \"MINERAL_LEASE\", \"instrument_number\": \"2026-ML-B544\", \"date_recorded\": \"04/11/2026\", \"verification_status\": \"INDEXED_AND_SEALED\"}",
    "[PARSED_DATA_ENTRY] | HASH: ea8b955f215fcd202b3c8b98c863da297913b40709b3b04a80526099a68d74c92b2a4329f126e2c62b91ee9c31f876cd83bfd42e0d6dc65bc0f6cd5e90006f34 | DATA: {\"timestamp\": \"2026-06-18T11:00:02.890125+00:00\", \"target_vector\": \"Taylor Winona\", \"document_type\": \"SUCCESSION_RECORD\", \"instrument_number\": \"2026-SR-T01\", \"date_recorded\": \"06/11/2026\", \"verification_status\": \"INDEXED_AND_SEALED\"}",
    "[PARSED_DATA_ENTRY] | HASH: 9a4cac5ccbaca07517db88f31085407f469f5ec8e2fcb8a2fbbe720b78dd5afcec7f741206a5f6c86bfb10c7e9525851bd42ae9c7e787202aeb00d8cbca40f25 | DATA: {\"timestamp\": \"2026-06-18T11:00:02.890285+00:00\", \"target_vector\": \"Miller Elizabeth\", \"document_type\": \"SUCCESSION_RECORD\", \"instrument_number\": \"2026-SR-M02\", \"date_recorded\": \"06/11/2026\", \"verification_status\": \"INDEXED_AND_SEALED\"}",
    "[PARSED_DATA_ENTRY] | HASH: bae8388fde0d1a2bcc72d9401d36a465c4450191fbc9adbbb69cce3d2afa6a9ad9ace1401e9821fcdbf9914f58722be58941a90de72d8aa646f387e29955f908 | DATA: {\"timestamp\": \"2026-06-18T11:00:02.969604+00:00\", \"target_vector\": \"Abstract 544\", \"document_type\": \"PRODUCTION_REPORT\", \"instrument_number\": \"RRC-A544-2026-05\", \"date_recorded\": \"06/11/2026\", \"verification_status\": \"AUDIT_VERIFIED\"}",
    "[PROBATE_ANCHOR] | DATA: {\"source\": \"JOCO_OPR_LEGACY\", \"vector\": \"PROBATE_DECREE\", \"status\": \"PENDING_VALIDATION\", \"timestamp\": \"2026-06-11T14:52:00Z\"}",
    "[PROBATE_ANCHOR] | DATA: {\"source\": \"JOCO_OPR_LEGACY\", \"vector\": \"HEIRSHIP_AFFIDAVIT\", \"status\": \"PENDING_VALIDATION\", \"timestamp\": \"2026-06-11T14:52:00Z\"}",
    "[PROBATE_ANCHOR] | DATA: {\"source\": \"JOCO_OPR_LEGACY\", \"vector\": \"TAX_ASSESSMENT_ROLL\", \"status\": \"PENDING_VALIDATION\", \"timestamp\": \"2026-06-11T14:52:00Z\"}",
    "[LINEAGE_VECTOR] | DATA: {\"name\": \"Winona Taylor\", \"role\": \"PROTECTED_LINEAGE_VECTOR\", \"status\": \"MONITORED_AND_SEALED\"}",
    "[LINEAGE_VECTOR] | DATA: {\"name\": \"Elizabeth Miller\", \"role\": \"PROTECTED_LINEAGE_VECTOR\", \"status\": \"MONITORED_AND_SEALED\"}",
    "[LINEAGE_VECTOR] | DATA: {\"name\": \"Laura Marie Jones\", \"role\": \"PROTECTED_LINEAGE_VECTOR\", \"status\": \"MONITORED_AND_SEALED\"}",
    "[LINEAGE_VECTOR] | DATA: {\"name\": \"Brandon Lynn Campbell\", \"role\": \"PROTECTED_LINEAGE_VECTOR\", \"status\": \"MONITORED_AND_SEALED\"}",
    "[LINEAGE_VECTOR] | DATA: {\"name\": \"Silas Elbert Bandy\", \"role\": \"PROTECTED_LINEAGE_VECTOR\", \"status\": \"MONITORED_AND_SEALED\"}",
    "[LINEAGE_VECTOR] | DATA: {\"name\": \"Bandy\", \"role\": \"PROTECTED_LINEAGE_VECTOR\", \"status\": \"MONITORED_AND_SEALED\"}",
    "[LINEAGE_VECTOR] | DATA: {\"name\": \"Campbell\", \"role\": \"PROTECTED_LINEAGE_VECTOR\", \"status\": \"MONITORED_AND_SEALED\"}",
    "[LINEAGE_VECTOR] | DATA: {\"name\": \"Delbert Lee Campbell\", \"role\": \"FATHER\", \"relation\": \"PATERNAL\"}",
    "[LINEAGE_VECTOR] | DATA: {\"name\": \"Laura Marie Jones\", \"role\": \"MOTHER\", \"relation\": \"MATERNAL\"}",
    "[LINEAGE_VECTOR] | DATA: {\"name\": \"Oscar Campbell\", \"role\": \"GRANDFATHER\", \"relation\": \"PATERNAL\"}",
    "[LINEAGE_VECTOR] | DATA: {\"name\": \"Elsie Campbell\", \"role\": \"GRANDMOTHER\", \"relation\": \"PATERNAL\"}",
    "[LINEAGE_VECTOR] | DATA: {\"name\": \"Cary Lynn Bandy\", \"role\": \"GRANDFATHER\", \"relation\": \"MATERNAL\"}",
    "[LINEAGE_VECTOR] | DATA: {\"name\": \"Winona Taylor\", \"role\": \"GRANDMOTHER\", \"relation\": \"MATERNAL\"}",
    "[LINEAGE_VECTOR] | DATA: {\"name\": \"Elizabeth Miller\", \"role\": \"ANCESTOR\", \"relation\": \"MATERNAL\"}",
    "[LINEAGE_VECTOR] | DATA: {\"name\": \"Silas Elbert Bandy\", \"role\": \"PATRIARCH\", \"relation\": \"MATERNAL\"}",
    "[LINEAGE_VECTOR] | DATA: {\"name\": \"Justin Lee Campbell\", \"role\": \"BROTHER\", \"relation\": \"SIBLING\"}",
    "[LINEAGE_VECTOR] | DATA: {\"name\": \"Travis Wayne Campbell\", \"role\": \"BROTHER\", \"relation\": \"SIBLING\"}",
    "[LINEAGE_VECTOR] | DATA: {\"name\": \"Kaley Marie\", \"role\": \"DAUGHTER\", \"relation\": \"SUCCESSOR\"}"
  ],
  "ancestral_tree": {
    "root": "Ancestral Lineage",
    "nodes": {
      "Campbell": [
        "Brandon Lynn Campbell"
      ],
      "Bandy": [
        "Silas Elbert Bandy"
      ],
      "Taylor": [
        "Winona Taylor"
      ],
      "Miller": [
        "Elizabeth Miller"
      ],
      "Jones": [
        "Laura Marie Jones"
      ]
    },
    "status": "FORENSIC_VECTOR_SEALED"
  }
}