{
  "manifest_metadata": {
    "operator_key": "Campbell; Bandy (Lynn) absolute",
    "generated_at": "2026-06-23T22:00:03.517707+00:00",
    "environment": "Termux / CivicAdvocate.OS"
  },
  "anchored_entries": [
    "[LINEAGE_ANCHOR] | TIMESTAMP: 2026-06-11T13:36:43Z | HASH: 92d5b789fe579127a1b158d207a9076ae11169db40846b0c6a4cd0d6a63823e89b81513f69a7985b4f78e5e87fd3c2e17ad8f3fb87f86ba4d480950a58ea5a0c | DATA: ROOT_ANCESTORS:Winona Taylor|Elizabeth Miller->MATERNAL_ANCHOR:Laura Marie Jones->PRIMARY_SUCCESSOR:Brandon Lynn Campbell->DESCENDANT:Daughter Node",
    "[PARSED_DATA_ENTRY] | HASH: 3124b390451b06b23c8f56bea234ed90811a9d5f444ab297a9dd9fed57ebb80394e2bd9344b328c7946069957055ff00602ab13bfffd1def2a764d7a9f459bf3 | DATA: {\"timestamp\": \"2026-06-23T22:00:03.342632+00:00\", \"target_vector\": \"Abstract 544\", \"document_type\": \"DEED\", \"instrument_number\": \"2026-A544-01\", \"date_recorded\": \"04/09/2026\", \"verification_status\": \"INDEXED_AND_SEALED\"}",
    "[PARSED_DATA_ENTRY] | HASH: 92a0a6baff05844690b06efefd48313b0067314f35913c27d47695fc8eddc43dd0e300ccd8855a61048e71dbca29b83c625d0b4b330d4d741407c55536eed2ac | DATA: {\"timestamp\": \"2026-06-23T22:00:03.343055+00:00\", \"target_vector\": \"Silas Elbert Bandy\", \"document_type\": \"MINERAL_LEASE\", \"instrument_number\": \"2026-ML-B544\", \"date_recorded\": \"04/11/2026\", \"verification_status\": \"INDEXED_AND_SEALED\"}",
    "[PARSED_DATA_ENTRY] | HASH: 9009d4ffcb82b8affd2def0d482819b8426208a3099156861d75c381b6a19170a4290e2c15e33fa7aa9980216f9cb061cd6a73d6666d181376fb5c38c0e2704e | DATA: {\"timestamp\": \"2026-06-23T22:00:03.343343+00:00\", \"target_vector\": \"Taylor Winona\", \"document_type\": \"SUCCESSION_RECORD\", \"instrument_number\": \"2026-SR-T01\", \"date_recorded\": \"06/11/2026\", \"verification_status\": \"INDEXED_AND_SEALED\"}",
    "[PARSED_DATA_ENTRY] | HASH: 52b9fab1ebeda2b0343476fd881ad17b010a6e1a25c7f4b09c24f091edc38015eddcfcb14aa63cf16dbc0c7d016febc242f808abbaff3067d368545d2d39737c | DATA: {\"timestamp\": \"2026-06-23T22:00:03.343563+00:00\", \"target_vector\": \"Miller Elizabeth\", \"document_type\": \"SUCCESSION_RECORD\", \"instrument_number\": \"2026-SR-M02\", \"date_recorded\": \"06/11/2026\", \"verification_status\": \"INDEXED_AND_SEALED\"}",
    "[PARSED_DATA_ENTRY] | HASH: f04bb43373f746921a956e56a45032e3d40eae04fc403483bff60482da7c11fd3f81f539767a1e594c06185dff29fe7f1740b846cabeaaf3f9e5f9862e819661 | DATA: {\"timestamp\": \"2026-06-23T22:00:03.433391+00:00\", \"target_vector\": \"Abstract 544\", \"document_type\": \"PRODUCTION_REPORT\", \"instrument_number\": \"RRC-A544-2026-05\", \"date_recorded\": \"06/11/2026\", \"verification_status\": \"AUDIT_VERIFIED\"}",
    "[PROBATE_ANCHOR] | DATA: {\"source\": \"JOCO_OPR_LEGACY\", \"vector\": \"PROBATE_DECREE\", \"status\": \"PENDING_VALIDATION\", \"timestamp\": \"2026-06-11T14:52:00Z\"}",
    "[PROBATE_ANCHOR] | DATA: {\"source\": \"JOCO_OPR_LEGACY\", \"vector\": \"HEIRSHIP_AFFIDAVIT\", \"status\": \"PENDING_VALIDATION\", \"timestamp\": \"2026-06-11T14:52:00Z\"}",
    "[PROBATE_ANCHOR] | DATA: {\"source\": \"JOCO_OPR_LEGACY\", \"vector\": \"TAX_ASSESSMENT_ROLL\", \"status\": \"PENDING_VALIDATION\", \"timestamp\": \"2026-06-11T14:52:00Z\"}",
    "[LINEAGE_VECTOR] | DATA: {\"name\": \"Winona Taylor\", \"role\": \"PROTECTED_LINEAGE_VECTOR\", \"status\": \"MONITORED_AND_SEALED\"}",
    "[LINEAGE_VECTOR] | DATA: {\"name\": \"Elizabeth Miller\", \"role\": \"PROTECTED_LINEAGE_VECTOR\", \"status\": \"MONITORED_AND_SEALED\"}",
    "[LINEAGE_VECTOR] | DATA: {\"name\": \"Laura Marie Jones\", \"role\": \"PROTECTED_LINEAGE_VECTOR\", \"status\": \"MONITORED_AND_SEALED\"}",
    "[LINEAGE_VECTOR] | DATA: {\"name\": \"Brandon Lynn Campbell\", \"role\": \"PROTECTED_LINEAGE_VECTOR\", \"status\": \"MONITORED_AND_SEALED\"}",
    "[LINEAGE_VECTOR] | DATA: {\"name\": \"Silas Elbert Bandy\", \"role\": \"PROTECTED_LINEAGE_VECTOR\", \"status\": \"MONITORED_AND_SEALED\"}",
    "[LINEAGE_VECTOR] | DATA: {\"name\": \"Bandy\", \"role\": \"PROTECTED_LINEAGE_VECTOR\", \"status\": \"MONITORED_AND_SEALED\"}",
    "[LINEAGE_VECTOR] | DATA: {\"name\": \"Campbell\", \"role\": \"PROTECTED_LINEAGE_VECTOR\", \"status\": \"MONITORED_AND_SEALED\"}",
    "[LINEAGE_VECTOR] | DATA: {\"name\": \"Delbert Lee Campbell\", \"role\": \"FATHER\", \"relation\": \"PATERNAL\"}",
    "[LINEAGE_VECTOR] | DATA: {\"name\": \"Laura Marie Jones\", \"role\": \"MOTHER\", \"relation\": \"MATERNAL\"}",
    "[LINEAGE_VECTOR] | DATA: {\"name\": \"Oscar Campbell\", \"role\": \"GRANDFATHER\", \"relation\": \"PATERNAL\"}",
    "[LINEAGE_VECTOR] | DATA: {\"name\": \"Elsie Campbell\", \"role\": \"GRANDMOTHER\", \"relation\": \"PATERNAL\"}",
    "[LINEAGE_VECTOR] | DATA: {\"name\": \"Cary Lynn Bandy\", \"role\": \"GRANDFATHER\", \"relation\": \"MATERNAL\"}",
    "[LINEAGE_VECTOR] | DATA: {\"name\": \"Winona Taylor\", \"role\": \"GRANDMOTHER\", \"relation\": \"MATERNAL\"}",
    "[LINEAGE_VECTOR] | DATA: {\"name\": \"Elizabeth Miller\", \"role\": \"ANCESTOR\", \"relation\": \"MATERNAL\"}",
    "[LINEAGE_VECTOR] | DATA: {\"name\": \"Silas Elbert Bandy\", \"role\": \"PATRIARCH\", \"relation\": \"MATERNAL\"}",
    "[LINEAGE_VECTOR] | DATA: {\"name\": \"Justin Lee Campbell\", \"role\": \"BROTHER\", \"relation\": \"SIBLING\"}",
    "[LINEAGE_VECTOR] | DATA: {\"name\": \"Travis Wayne Campbell\", \"role\": \"BROTHER\", \"relation\": \"SIBLING\"}",
    "[LINEAGE_VECTOR] | DATA: {\"name\": \"Kaley Marie\", \"role\": \"DAUGHTER\", \"relation\": \"SUCCESSOR\"}"
  ],
  "ancestral_tree": {
    "root": "Ancestral Lineage",
    "nodes": {
      "Campbell": [
        "Brandon Lynn Campbell"
      ],
      "Bandy": [
        "Silas Elbert Bandy"
      ],
      "Taylor": [
        "Winona Taylor"
      ],
      "Miller": [
        "Elizabeth Miller"
      ],
      "Jones": [
        "Laura Marie Jones"
      ]
    },
    "status": "FORENSIC_VECTOR_SEALED"
  }
}